Metadata-Version: 2.4
Name: md2pdf-cli
Version: 0.1.0
Summary: A command-line tool to convert Markdown files to PDF
Home-page: https://github.com/yourusername/md2pdf
Author: Your Name
Author-email: your.email@example.com
Project-URL: Bug Reports, https://github.com/yourusername/md2pdf/issues
Project-URL: Source, https://github.com/yourusername/md2pdf
Keywords: markdown pdf conversion cli
Classifier: Development Status :: 4 - Beta
Classifier: Environment :: Console
Classifier: Intended Audience :: Developers
Classifier: License :: OSI Approved :: MIT License
Classifier: Operating System :: OS Independent
Classifier: Programming Language :: Python :: 3
Classifier: Programming Language :: Python :: 3.7
Classifier: Programming Language :: Python :: 3.8
Classifier: Programming Language :: Python :: 3.9
Classifier: Programming Language :: Python :: 3.10
Classifier: Programming Language :: Python :: 3.11
Classifier: Topic :: Documentation
Classifier: Topic :: Multimedia :: Graphics :: Graphics Conversion
Classifier: Topic :: Text Processing :: Markup
Requires-Python: >=3.7
License-File: LICENSE
Requires-Dist: markdown2
Requires-Dist: pdfkit
Dynamic: author
Dynamic: author-email
Dynamic: classifier
Dynamic: description
Dynamic: description-content-type
Dynamic: home-page
Dynamic: keywords
Dynamic: license-file
Dynamic: project-url
Dynamic: requires-dist
Dynamic: requires-python
Dynamic: summary
